lesscode_options/__init__.py
lesscode_options/options.py
lesscode_options-0.0.1.dist-info/METADATA
lesscode_options-0.0.1.dist-info/WHEEL
lesscode_options-0.0.1.dist-info/licenses/LICENSE
lesscode_options-0.0.1.dist-info/RECORD
