Metadata-Version: 2.1
Name: lesscode-options
Version: 0.0.1
Summary: lesscode_options是自定义全局配置项，一个地方定义，全局使用
Author-email: navysummer <navysummer@yeah.net>
License:                                  Apache License
License-File: LICENSE
Classifier: License :: OSI Approved :: MIT License
Classifier: Operating System :: OS Independent
Classifier: Programming Language :: Python :: 3
Requires-Python: >=3.7
